ManimTool/__init__.py
ManimTool/main.py
ManimTool-0.1.2.0.dist-info/METADATA
ManimTool-0.1.2.0.dist-info/WHEEL
ManimTool-0.1.2.0.dist-info/top_level.txt
ManimTool-0.1.2.0.dist-info/RECORD
