Metadata-Version: 2.1
Name: ManimTool
Version: 0.1.2.0
Summary: A package for tools in Manim
Author: Zhu Chongjing
Author-email: zhuchongjing_pypi@163.com
Classifier: Programming Language :: Python :: 3
Classifier: License :: OSI Approved :: MIT License
Classifier: Operating System :: OS Independent
Requires-Dist: manim
